cameron/__init__.py
cameron/cli.py
cameron/routes.py
cameron/state.py
tok715_cameron-0.1.0.dist-info/LICENSE
tok715_cameron-0.1.0.dist-info/METADATA
tok715_cameron-0.1.0.dist-info/WHEEL
tok715_cameron-0.1.0.dist-info/entry_points.txt
tok715_cameron-0.1.0.dist-info/RECORD
