Metadata-Version: 2.1
Name: tok715-cameron
Version: 0.1.0
Summary: monolith application for tok715/cameron artificial intelligence
License: MIT
Author: GUO YANKE
Author-email: hi@guoyk.xyz
Requires-Python: >=3.10,<4.0
Classifier: License :: OSI Approved :: MIT License
Classifier: Programming Language :: Python :: 3
Classifier: Programming Language :: Python :: 3.10
Classifier: Programming Language :: Python :: 3.11
Requires-Dist: click (>=8.1.7,<9.0.0)
Requires-Dist: starlette (>=0.32.0.post1,<0.33.0)
Requires-Dist: uvicorn (>=0.24.0.post1,<0.25.0)
